py_bark_client/__init__.py
py_bark_client/py_bark_client.py
py_bark_client-0.0.1.dist-info/LICENSE
py_bark_client-0.0.1.dist-info/METADATA
py_bark_client-0.0.1.dist-info/WHEEL
py_bark_client-0.0.1.dist-info/top_level.txt
py_bark_client-0.0.1.dist-info/RECORD
