Metadata-Version: 2.1
Name: py-bark-client
Version: 0.0.1
Summary: Bark client for Python
Home-page: https://github.com/rockiecxh/py-bark-client
Author: Rockie Cui
Author-email: rockiecxh@gmail.com
License: UNKNOWN
Project-URL: Bug Tracker, https://github.com/rockiecxh/py-bark-client/issues
Platform: UNKNOWN
Classifier: Programming Language :: Python :: 3
Classifier: Programming Language :: Python :: 3.5
Classifier: Programming Language :: Python :: 3.6
Classifier: Programming Language :: Python :: 3.7
Classifier: Programming Language :: Python :: 3.8
Classifier: Programming Language :: Python :: 3.9
Classifier: Programming Language :: Python :: 3.10
Classifier: License :: OSI Approved :: MIT License
Classifier: Operating System :: OS Independent
Requires-Python: >=3.5
Requires-Dist: requests (>=2.25.1)
